stake/__init__.py
stake/asx/__init__.py
stake/asx/common.py
stake/asx/equity.py
stake/asx/funding.py
stake/asx/market.py
stake/asx/order.py
stake/asx/product.py
stake/asx/trade.py
stake/asx/transaction.py
stake/client.py
stake/common.py
stake/constant.py
stake/equity.py
stake/funding.py
stake/fx.py
stake/market.py
stake/order.py
stake/product.py
stake/ratings.py
stake/statement.py
stake/trade.py
stake/transaction.py
stake/user.py
stake/watchlist.py
stake-0.12.0.dist-info/LICENSE.md
stake-0.12.0.dist-info/METADATA
stake-0.12.0.dist-info/WHEEL
stake-0.12.0.dist-info/RECORD
