Metadata-Version: 2.3
Name: stake
Version: 0.12.0
Summary: Unofficial  https://hellostake.com API wrapper.
License: Apache-2.0
Keywords: stake,trading,stocks,financial,python
Author: Stefano Tabacco
Author-email: tabacco.stefano@gmail.com
Requires-Python: >=3.10,<4.0.0
Classifier: License :: OSI Approved :: Apache Software License
Classifier: Programming Language :: Python :: 3
Classifier: Programming Language :: Python :: 3.10
Classifier: Programming Language :: Python :: 3.11
Classifier: Programming Language :: Python :: 3.12
Classifier: Programming Language :: Python :: 3.13
Requires-Dist: aiohttp (>=3.9,<4.0)
Requires-Dist: inflection (>=0.5.0,<0.6.0)
Requires-Dist: pydantic (>=2.3,<3.0)
Requires-Dist: python-dotenv (>=0.13.0,<0.14.0)
Requires-Dist: single-version (>=1.2.2,<2.0.0)
Project-URL: Homepage, https://github.com/stabacco/stake-python
Project-URL: Repository, https://github.com/stabacco/stake-python
